qitangle/__init__.py
qitangle/cantrips.py
qitangle/tangle.py
qitangle-0.1.3.dist-info/licenses/LICENSE
qitangle-0.1.3.dist-info/WHEEL
qitangle-0.1.3.dist-info/METADATA
qitangle-0.1.3.dist-info/RECORD
