Metadata-Version: 2.4
Name: qitangle
Version: 0.1.3
Summary: QiTangle - IPython magic to tangle (quarto) specified code cells into python source files
Author-email: Fenke Meijer <fenkemeijer@gmail.com>
License-Expression: GPL-3.0-or-later
License-File: LICENSE
Project-URL: Home, https://codeberg.org/fenke/exce
